LICENSE
MANIFEST.in
README.rst
requirements-test.txt
setup.py
django_random_queryset/__init__.py
django_random_queryset/managers.py
django_random_queryset/queryset.py
django_random_queryset/strategies.py
django_random_queryset.egg-info/PKG-INFO
django_random_queryset.egg-info/SOURCES.txt
django_random_queryset.egg-info/dependency_links.txt
django_random_queryset.egg-info/requires.txt
django_random_queryset.egg-info/top_level.txt